ProgramizJavaJiaochengChuyi/README.md
ProgramizJavaJiaochengChuyi/__init__.py
ProgramizJavaJiaochengChuyi/__main__.py
ProgramizJavaJiaochengChuyi/file.epub
ProgramizJavaJiaochengChuyi/index.html
ProgramizJavaJiaochengChuyi/css/__init__.py
ProgramizJavaJiaochengChuyi/css/annotations.css
ProgramizJavaJiaochengChuyi/css/main.css
ProgramizJavaJiaochengChuyi/css/normalize.css
ProgramizJavaJiaochengChuyi/css/popup.css
ProgramizJavaJiaochengChuyi/font/__init__.py
ProgramizJavaJiaochengChuyi/font/fontello.eot
ProgramizJavaJiaochengChuyi/font/fontello.svg
ProgramizJavaJiaochengChuyi/font/fontello.ttf
ProgramizJavaJiaochengChuyi/font/fontello.woff
ProgramizJavaJiaochengChuyi/img/__init__.py
ProgramizJavaJiaochengChuyi/img/annotator-glyph-sprite.png
ProgramizJavaJiaochengChuyi/img/annotator-icon-sprite.png
ProgramizJavaJiaochengChuyi/img/apple-touch-icon.png
ProgramizJavaJiaochengChuyi/img/cancelfullscreen.png
ProgramizJavaJiaochengChuyi/img/close.png
ProgramizJavaJiaochengChuyi/img/fullscreen.png
ProgramizJavaJiaochengChuyi/img/loader.gif
ProgramizJavaJiaochengChuyi/img/menu-icon.png
ProgramizJavaJiaochengChuyi/img/save.png
ProgramizJavaJiaochengChuyi/img/saved.png
ProgramizJavaJiaochengChuyi/img/settings-s.png
ProgramizJavaJiaochengChuyi/img/settings.png
ProgramizJavaJiaochengChuyi/img/star.png
ProgramizJavaJiaochengChuyi/js/__init__.py
ProgramizJavaJiaochengChuyi/js/epub.js
ProgramizJavaJiaochengChuyi/js/epub.min.js
ProgramizJavaJiaochengChuyi/js/epub.min.map
ProgramizJavaJiaochengChuyi/js/hooks.min.js
ProgramizJavaJiaochengChuyi/js/hooks.min.map
ProgramizJavaJiaochengChuyi/js/reader.js
ProgramizJavaJiaochengChuyi/js/reader.js.map
ProgramizJavaJiaochengChuyi/js/reader.min.js
ProgramizJavaJiaochengChuyi/js/reader.min.map
ProgramizJavaJiaochengChuyi/js/hooks/__init__.py
ProgramizJavaJiaochengChuyi/js/hooks/extensions/__init__.py
ProgramizJavaJiaochengChuyi/js/hooks/extensions/highlight.js
ProgramizJavaJiaochengChuyi/js/libs/__init__.py
programiz_java_jiaocheng_chuyi-2024.3.5.0.dist-info/METADATA
programiz_java_jiaocheng_chuyi-2024.3.5.0.dist-info/WHEEL
programiz_java_jiaocheng_chuyi-2024.3.5.0.dist-info/entry_points.txt
programiz_java_jiaocheng_chuyi-2024.3.5.0.dist-info/top_level.txt
programiz_java_jiaocheng_chuyi-2024.3.5.0.dist-info/RECORD
